{"etag":"\"XI7nbFXulYBIpL0ayR_gDh3eu1k\/cWb4VrexKlK9NdunOJ1LM2Bt6A4\"","eventId":null,"kind":"youtube#playlistItemListResponse","nextPageToken":null,"prevPageToken":null,"visitorId":null,"pageInfo":{"resultsPerPage":50,"totalResults":8},"items":[{"etag":"\"XI7nbFXulYBIpL0ayR_gDh3eu1k\/wDQIKrmDjKtuvh0wvN3xyGF-kQ0\"","id":"UExrVlJKZlVuTFJOS0EzcmluNHJCUG5nbEdQbDVpcHcwWS4yODlGNEE0NkRGMEEzMEQy","kind":"youtube#playlistItem","snippet":{"channelId":"UCcvatGFnbYUCgXRapk1dMvw","channelTitle":"Chandra X-ray Observatory","description":"","playlistId":"PLkVRJfUnLRNKA3rin4rBPnglGPl5ipw0Y","position":0,"publishedAt":"2015-11-06T14:38:35.000Z","title":"Science Olympiad Reach for the Stars Event 2016 Part1","thumbnails":{"default":{"height":90,"url":"https:\/\/i.ytimg.com\/vi\/cV9WMjg0WiU\/default.jpg","width":120},"medium":{"height":180,"url":"https:\/\/i.ytimg.com\/vi\/cV9WMjg0WiU\/mqdefault.jpg","width":320},"high":{"height":360,"url":"https:\/\/i.ytimg.com\/vi\/cV9WMjg0WiU\/hqdefault.jpg","width":480},"standard":{"height":480,"url":"https:\/\/i.ytimg.com\/vi\/cV9WMjg0WiU\/sddefault.jpg","width":640}},"resourceId":{"channelId":null,"kind":"youtube#video","playlistId":null,"videoId":"cV9WMjg0WiU"}},"contentDetails":{"endAt":null,"note":null,"startAt":null,"videoId":"cV9WMjg0WiU","videoPublishedAt":"2015-11-06T14:38:34.000Z"}},{"etag":"\"XI7nbFXulYBIpL0ayR_gDh3eu1k\/D9HOkRJUPwzmnOVM598_zFk19hw\"","id":"UExrVlJKZlVuTFJOS0EzcmluNHJCUG5nbEdQbDVpcHcwWS41MjE1MkI0OTQ2QzJGNzNG","kind":"youtube#playlistItem","snippet":{"channelId":"UCcvatGFnbYUCgXRapk1dMvw","channelTitle":"Chandra X-ray Observatory","description":"","playlistId":"PLkVRJfUnLRNKA3rin4rBPnglGPl5ipw0Y","position":1,"publishedAt":"2015-11-06T14:39:51.000Z","title":"Science Olympiad Reach for the Stars Event 2016 Part2","thumbnails":{"default":{"height":90,"url":"https:\/\/i.ytimg.com\/vi\/DtJGr6dYxV0\/default.jpg","width":120},"medium":{"height":180,"url":"https:\/\/i.ytimg.com\/vi\/DtJGr6dYxV0\/mqdefault.jpg","width":320},"high":{"height":360,"url":"https:\/\/i.ytimg.com\/vi\/DtJGr6dYxV0\/hqdefault.jpg","width":480},"standard":{"height":480,"url":"https:\/\/i.ytimg.com\/vi\/DtJGr6dYxV0\/sddefault.jpg","width":640},"maxres":{"height":720,"url":"https:\/\/i.ytimg.com\/vi\/DtJGr6dYxV0\/maxresdefault.jpg","width":1280}},"resourceId":{"channelId":null,"kind":"youtube#video","playlistId":null,"videoId":"DtJGr6dYxV0"}},"contentDetails":{"endAt":null,"note":null,"startAt":null,"videoId":"DtJGr6dYxV0","videoPublishedAt":"2015-11-06T14:38:34.000Z"}},{"etag":"\"XI7nbFXulYBIpL0ayR_gDh3eu1k\/GugPwQj60oqxQvOIrmE3oY8hnL4\"","id":"UExrVlJKZlVuTFJOS0EzcmluNHJCUG5nbEdQbDVpcHcwWS41NkI0NEY2RDEwNTU3Q0M2","kind":"youtube#playlistItem","snippet":{"channelId":"UCcvatGFnbYUCgXRapk1dMvw","channelTitle":"Chandra X-ray Observatory","description":"","playlistId":"PLkVRJfUnLRNKA3rin4rBPnglGPl5ipw0Y","position":2,"publishedAt":"2015-11-06T14:38:34.000Z","title":"Science Olympiad Reach for the Stars Event 2016 Part3","thumbnails":{"default":{"height":90,"url":"https:\/\/i.ytimg.com\/vi\/MMwnz4zbGl4\/default.jpg","width":120},"medium":{"height":180,"url":"https:\/\/i.ytimg.com\/vi\/MMwnz4zbGl4\/mqdefault.jpg","width":320},"high":{"height":360,"url":"https:\/\/i.ytimg.com\/vi\/MMwnz4zbGl4\/hqdefault.jpg","width":480},"standard":{"height":480,"url":"https:\/\/i.ytimg.com\/vi\/MMwnz4zbGl4\/sddefault.jpg","width":640},"maxres":{"height":720,"url":"https:\/\/i.ytimg.com\/vi\/MMwnz4zbGl4\/maxresdefault.jpg","width":1280}},"resourceId":{"channelId":null,"kind":"youtube#video","playlistId":null,"videoId":"MMwnz4zbGl4"}},"contentDetails":{"endAt":null,"note":null,"startAt":null,"videoId":"MMwnz4zbGl4","videoPublishedAt":"2015-11-06T14:38:34.000Z"}},{"etag":"\"XI7nbFXulYBIpL0ayR_gDh3eu1k\/wVp6hcVQIy7-Zqpks1EjnNBxQB8\"","id":"UExrVlJKZlVuTFJOS0EzcmluNHJCUG5nbEdQbDVpcHcwWS4wMTcyMDhGQUE4NTIzM0Y5","kind":"youtube#playlistItem","snippet":{"channelId":"UCcvatGFnbYUCgXRapk1dMvw","channelTitle":"Chandra X-ray Observatory","description":"","playlistId":"PLkVRJfUnLRNKA3rin4rBPnglGPl5ipw0Y","position":3,"publishedAt":"2015-11-06T14:38:35.000Z","title":"Science Olympiad Reach for the Stars Event 2016 Part4","thumbnails":{"default":{"height":90,"url":"https:\/\/i.ytimg.com\/vi\/OrKn25Og4-c\/default.jpg","width":120},"medium":{"height":180,"url":"https:\/\/i.ytimg.com\/vi\/OrKn25Og4-c\/mqdefault.jpg","width":320},"high":{"height":360,"url":"https:\/\/i.ytimg.com\/vi\/OrKn25Og4-c\/hqdefault.jpg","width":480},"standard":{"height":480,"url":"https:\/\/i.ytimg.com\/vi\/OrKn25Og4-c\/sddefault.jpg","width":640},"maxres":{"height":720,"url":"https:\/\/i.ytimg.com\/vi\/OrKn25Og4-c\/maxresdefault.jpg","width":1280}},"resourceId":{"channelId":null,"kind":"youtube#video","playlistId":null,"videoId":"OrKn25Og4-c"}},"contentDetails":{"endAt":null,"note":null,"startAt":null,"videoId":"OrKn25Og4-c","videoPublishedAt":"2015-11-06T14:38:34.000Z"}},{"etag":"\"XI7nbFXulYBIpL0ayR_gDh3eu1k\/W3mzzXHVDPfd1KVMTZI9kem0_DY\"","id":"UExrVlJKZlVuTFJOS0EzcmluNHJCUG5nbEdQbDVpcHcwWS4wOTA3OTZBNzVEMTUzOTMy","kind":"youtube#playlistItem","snippet":{"channelId":"UCcvatGFnbYUCgXRapk1dMvw","channelTitle":"Chandra X-ray Observatory","description":"","playlistId":"PLkVRJfUnLRNKA3rin4rBPnglGPl5ipw0Y","position":4,"publishedAt":"2015-11-06T14:40:11.000Z","title":"Science Olympiad Reach for the Stars Event 2016 Part5","thumbnails":{"default":{"height":90,"url":"https:\/\/i.ytimg.com\/vi\/t40o7NKGnC0\/default.jpg","width":120},"medium":{"height":180,"url":"https:\/\/i.ytimg.com\/vi\/t40o7NKGnC0\/mqdefault.jpg","width":320},"high":{"height":360,"url":"https:\/\/i.ytimg.com\/vi\/t40o7NKGnC0\/hqdefault.jpg","width":480},"standard":{"height":480,"url":"https:\/\/i.ytimg.com\/vi\/t40o7NKGnC0\/sddefault.jpg","width":640},"maxres":{"height":720,"url":"https:\/\/i.ytimg.com\/vi\/t40o7NKGnC0\/maxresdefault.jpg","width":1280}},"resourceId":{"channelId":null,"kind":"youtube#video","playlistId":null,"videoId":"t40o7NKGnC0"}},"contentDetails":{"endAt":null,"note":null,"startAt":null,"videoId":"t40o7NKGnC0","videoPublishedAt":"2015-11-06T14:38:34.000Z"}},{"etag":"\"XI7nbFXulYBIpL0ayR_gDh3eu1k\/lQH_O80oKBPIGJ37B-5ljv-H5So\"","id":"UExrVlJKZlVuTFJOS0EzcmluNHJCUG5nbEdQbDVpcHcwWS4xMkVGQjNCMUM1N0RFNEUx","kind":"youtube#playlistItem","snippet":{"channelId":"UCcvatGFnbYUCgXRapk1dMvw","channelTitle":"Chandra X-ray Observatory","description":"","playlistId":"PLkVRJfUnLRNKA3rin4rBPnglGPl5ipw0Y","position":5,"publishedAt":"2015-11-17T16:13:41.000Z","title":"State Directors & Event Supervisors Guide RFTS2016 Part 1","thumbnails":{"default":{"height":90,"url":"https:\/\/i.ytimg.com\/vi\/G2GURwuti44\/default.jpg","width":120},"medium":{"height":180,"url":"https:\/\/i.ytimg.com\/vi\/G2GURwuti44\/mqdefault.jpg","width":320},"high":{"height":360,"url":"https:\/\/i.ytimg.com\/vi\/G2GURwuti44\/hqdefault.jpg","width":480},"standard":{"height":480,"url":"https:\/\/i.ytimg.com\/vi\/G2GURwuti44\/sddefault.jpg","width":640},"maxres":{"height":720,"url":"https:\/\/i.ytimg.com\/vi\/G2GURwuti44\/maxresdefault.jpg","width":1280}},"resourceId":{"channelId":null,"kind":"youtube#video","playlistId":null,"videoId":"G2GURwuti44"}},"contentDetails":{"endAt":null,"note":null,"startAt":null,"videoId":"G2GURwuti44","videoPublishedAt":"2015-11-17T16:05:23.000Z"}},{"etag":"\"XI7nbFXulYBIpL0ayR_gDh3eu1k\/hzMreBo6h6UrDWGGEhNjNfLAiB0\"","id":"UExrVlJKZlVuTFJOS0EzcmluNHJCUG5nbEdQbDVpcHcwWS41MzJCQjBCNDIyRkJDN0VD","kind":"youtube#playlistItem","snippet":{"channelId":"UCcvatGFnbYUCgXRapk1dMvw","channelTitle":"Chandra X-ray Observatory","description":"","playlistId":"PLkVRJfUnLRNKA3rin4rBPnglGPl5ipw0Y","position":6,"publishedAt":"2015-11-17T16:13:41.000Z","title":"State Directors & Event Supervisors Guide RFTS2016 Part 2","thumbnails":{"default":{"height":90,"url":"https:\/\/i.ytimg.com\/vi\/cjo2uxtWTVc\/default.jpg","width":120},"medium":{"height":180,"url":"https:\/\/i.ytimg.com\/vi\/cjo2uxtWTVc\/mqdefault.jpg","width":320},"high":{"height":360,"url":"https:\/\/i.ytimg.com\/vi\/cjo2uxtWTVc\/hqdefault.jpg","width":480},"standard":{"height":480,"url":"https:\/\/i.ytimg.com\/vi\/cjo2uxtWTVc\/sddefault.jpg","width":640},"maxres":{"height":720,"url":"https:\/\/i.ytimg.com\/vi\/cjo2uxtWTVc\/maxresdefault.jpg","width":1280}},"resourceId":{"channelId":null,"kind":"youtube#video","playlistId":null,"videoId":"cjo2uxtWTVc"}},"contentDetails":{"endAt":null,"note":null,"startAt":null,"videoId":"cjo2uxtWTVc","videoPublishedAt":"2015-11-17T16:05:23.000Z"}},{"etag":"\"XI7nbFXulYBIpL0ayR_gDh3eu1k\/GkCXZYB3CS3klkPmPp-KFanbqPE\"","id":"UExrVlJKZlVuTFJOS0EzcmluNHJCUG5nbEdQbDVpcHcwWS5DQUNERDQ2NkIzRUQxNTY1","kind":"youtube#playlistItem","snippet":{"channelId":"UCcvatGFnbYUCgXRapk1dMvw","channelTitle":"Chandra X-ray Observatory","description":"","playlistId":"PLkVRJfUnLRNKA3rin4rBPnglGPl5ipw0Y","position":7,"publishedAt":"2015-11-17T16:13:41.000Z","title":"State Directors & Event Supervisors Guide RFTS2016 Part 3","thumbnails":{"default":{"height":90,"url":"https:\/\/i.ytimg.com\/vi\/nQi7FS-s4Xg\/default.jpg","width":120},"medium":{"height":180,"url":"https:\/\/i.ytimg.com\/vi\/nQi7FS-s4Xg\/mqdefault.jpg","width":320},"high":{"height":360,"url":"https:\/\/i.ytimg.com\/vi\/nQi7FS-s4Xg\/hqdefault.jpg","width":480},"standard":{"height":480,"url":"https:\/\/i.ytimg.com\/vi\/nQi7FS-s4Xg\/sddefault.jpg","width":640},"maxres":{"height":720,"url":"https:\/\/i.ytimg.com\/vi\/nQi7FS-s4Xg\/maxresdefault.jpg","width":1280}},"resourceId":{"channelId":null,"kind":"youtube#video","playlistId":null,"videoId":"nQi7FS-s4Xg"}},"contentDetails":{"endAt":null,"note":null,"startAt":null,"videoId":"nQi7FS-s4Xg","videoPublishedAt":"2015-11-17T16:05:23.000Z"}}]}